{
  "fio version" : "fio-3.7",
  "timestamp" : 1580331623,
  "timestamp_ms" : 1580331623620,
  "time" : "Wed Jan 29 14:00:23 2020",
  "global options" : {
    "filename" : "/dev/md/MD-001-sda-sdb",
    "direct" : "1",
    "rw" : "randread",
    "ioengine" : "libaio",
    "iodepth" : "32",
    "numjobs" : "1",
    "runtime" : "360"
  },
  "jobs" : [
    {
      "jobname" : "direct-randread-1M",
      "groupid" : 0,
      "error" : 0,
      "eta" : 0,
      "elapsed" : 361,
      "job options" : {
        "name" : "direct-randread-1M",
        "bs" : "1M"
      },
      "read" : {
        "io_bytes" : 43824185344,
        "io_kbytes" : 42797056,
        "bw_bytes" : 121648356,
        "bw" : 118797,
        "iops" : 116.012913,
        "runtime" : 360253,
        "total_ios" : 41794,
        "short_ios" : 0,
        "drop_ios" : 0,
        "slat_ns" : {
          "min" : 135525,
          "max" : 967543,
          "mean" : 435570.316935,
          "stddev" : 182894.589415
        },
        "clat_ns" : {
          "min" : 7269691,
          "max" : 2432298268,
          "mean" : 275378426.906810,
          "stddev" : 191574068.337931,
          "percentile" : {
            "1.000000" : 23724032,
            "5.000000" : 50593792,
            "10.000000" : 76021760,
            "20.000000" : 117964800,
            "30.000000" : 158334976,
            "40.000000" : 196083712,
            "50.000000" : 235929600,
            "60.000000" : 278921216,
            "70.000000" : 333447168,
            "80.000000" : 400556032,
            "90.000000" : 522190848,
            "95.000000" : 641728512,
            "99.000000" : 910163968,
            "99.500000" : 1035993088,
            "99.900000" : 1317011456,
            "99.950000" : 1468006400,
            "99.990000" : 1937768448
          },
          "bins" : {
            "7241728" : 1,
            "7766016" : 1,
            "8093696" : 1,
            "8454144" : 1,
            "9371648" : 1,
            "9502720" : 1,
            "9895936" : 1,
            "10420224" : 1,
            "10551296" : 1,
            "10944512" : 2,
            "11075584" : 1,
            "11599872" : 1,
            "11730944" : 3,
            "11862016" : 1,
            "11993088" : 2,
            "12255232" : 5,
            "12517376" : 3,
            "12648448" : 1,
            "12779520" : 2,
            "12910592" : 1,
            "13041664" : 5,
            "13172736" : 1,
            "13303808" : 3,
            "13565952" : 2,
            "13697024" : 5,
            "13828096" : 5,
            "13959168" : 2,
            "14090240" : 1,
            "14221312" : 3,
            "14352384" : 4,
            "14483456" : 2,
            "14614528" : 2,
            "14745600" : 4,
            "14876672" : 5,
            "15007744" : 4,
            "15138816" : 2,
            "15269888" : 4,
            "15400960" : 8,
            "15532032" : 7,
            "15663104" : 1,
            "15794176" : 4,
            "15925248" : 6,
            "16056320" : 4,
            "16187392" : 10,
            "16318464" : 7,
            "16449536" : 6,
            "16580608" : 6,
            "16711680" : 13,
            "16908288" : 6,
            "17170432" : 7,
            "17432576" : 13,
            "17694720" : 6,
            "17956864" : 9,
            "18219008" : 7,
            "18481152" : 14,
            "18743296" : 6,
            "19005440" : 9,
            "19267584" : 8,
            "19529728" : 11,
            "19791872" : 7,
            "20054016" : 6,
            "20316160" : 8,
            "20578304" : 9,
            "20840448" : 8,
            "21102592" : 7,
            "21364736" : 10,
            "21626880" : 12,
            "21889024" : 13,
            "22151168" : 8,
            "22413312" : 10,
            "22675456" : 17,
            "22937600" : 8,
            "23199744" : 8,
            "23461888" : 14,
            "23724032" : 20,
            "23986176" : 15,
            "24248320" : 14,
            "24510464" : 13,
            "24772608" : 17,
            "25034752" : 10,
            "25296896" : 23,
            "25559040" : 17,
            "25821184" : 20,
            "26083328" : 8,
            "26345472" : 10,
            "26607616" : 18,
            "26869760" : 20,
            "27131904" : 19,
            "27394048" : 7,
            "27656192" : 14,
            "27918336" : 8,
            "28180480" : 10,
            "28442624" : 15,
            "28704768" : 11,
            "28966912" : 7,
            "29229056" : 21,
            "29491200" : 14,
            "29753344" : 13,
            "30015488" : 14,
            "30277632" : 10,
            "30539776" : 13,
            "30801920" : 11,
            "31064064" : 16,
            "31326208" : 22,
            "31588352" : 10,
            "31850496" : 12,
            "32112640" : 12,
            "32374784" : 12,
            "32636928" : 14,
            "32899072" : 25,
            "33161216" : 19,
            "33423360" : 16,
            "33816576" : 30,
            "34340864" : 38,
            "34865152" : 36,
            "35389440" : 32,
            "35913728" : 45,
            "36438016" : 28,
            "36962304" : 35,
            "37486592" : 29,
            "38010880" : 30,
            "38535168" : 29,
            "39059456" : 33,
            "39583744" : 27,
            "40108032" : 30,
            "40632320" : 28,
            "41156608" : 31,
            "41680896" : 42,
            "42205184" : 33,
            "42729472" : 45,
            "43253760" : 42,
            "43778048" : 39,
            "44302336" : 49,
            "44826624" : 39,
            "45350912" : 28,
            "45875200" : 40,
            "46399488" : 40,
            "46923776" : 37,
            "47448064" : 34,
            "47972352" : 38,
            "48496640" : 31,
            "49020928" : 41,
            "49545216" : 39,
            "50069504" : 36,
            "50593792" : 53,
            "51118080" : 43,
            "51642368" : 43,
            "52166656" : 45,
            "52690944" : 33,
            "53215232" : 36,
            "53739520" : 47,
            "54263808" : 39,
            "54788096" : 30,
            "55312384" : 38,
            "55836672" : 38,
            "56360960" : 32,
            "56885248" : 37,
            "57409536" : 39,
            "57933824" : 42,
            "58458112" : 43,
            "58982400" : 46,
            "59506688" : 36,
            "60030976" : 40,
            "60555264" : 42,
            "61079552" : 41,
            "61603840" : 49,
            "62128128" : 46,
            "62652416" : 42,
            "63176704" : 49,
            "63700992" : 38,
            "64225280" : 40,
            "64749568" : 44,
            "65273856" : 42,
            "65798144" : 51,
            "66322432" : 42,
            "66846720" : 47,
            "67633152" : 96,
            "68681728" : 94,
            "69730304" : 97,
            "70778880" : 101,
            "71827456" : 91,
            "72876032" : 86,
            "73924608" : 93,
            "74973184" : 100,
            "76021760" : 109,
            "77070336" : 103,
            "78118912" : 104,
            "79167488" : 100,
            "80216064" : 99,
            "81264640" : 84,
            "82313216" : 88,
            "83361792" : 82,
            "84410368" : 99,
            "85458944" : 94,
            "86507520" : 100,
            "87556096" : 117,
            "88604672" : 108,
            "89653248" : 103,
            "90701824" : 78,
            "91750400" : 109,
            "92798976" : 100,
            "93847552" : 109,
            "94896128" : 102,
            "95944704" : 96,
            "96993280" : 93,
            "98041856" : 113,
            "99090432" : 94,
            "100139008" : 88,
            "101187584" : 119,
            "102236160" : 103,
            "103284736" : 108,
            "104333312" : 116,
            "105381888" : 110,
            "106430464" : 95,
            "107479040" : 94,
            "108527616" : 96,
            "109576192" : 119,
            "110624768" : 129,
            "111673344" : 115,
            "112721920" : 118,
            "113770496" : 101,
            "114819072" : 97,
            "115867648" : 117,
            "116916224" : 107,
            "117964800" : 110,
            "119013376" : 113,
            "120061952" : 103,
            "121110528" : 125,
            "122159104" : 112,
            "123207680" : 115,
            "124256256" : 109,
            "125304832" : 99,
            "126353408" : 114,
            "127401984" : 115,
            "128450560" : 118,
            "129499136" : 126,
            "130547712" : 94,
            "131596288" : 108,
            "132644864" : 102,
            "133693440" : 111,
            "135266304" : 211,
            "137363456" : 225,
            "139460608" : 206,
            "141557760" : 212,
            "143654912" : 221,
            "145752064" : 217,
            "147849216" : 217,
            "149946368" : 236,
            "152043520" : 230,
            "154140672" : 218,
            "156237824" : 241,
            "158334976" : 239,
            "160432128" : 220,
            "162529280" : 237,
            "164626432" : 224,
            "166723584" : 258,
            "168820736" : 210,
            "170917888" : 243,
            "173015040" : 259,
            "175112192" : 231,
            "177209344" : 215,
            "179306496" : 215,
            "181403648" : 228,
            "183500800" : 215,
            "185597952" : 245,
            "187695104" : 234,
            "189792256" : 231,
            "191889408" : 215,
            "193986560" : 229,
            "196083712" : 229,
            "198180864" : 235,
            "200278016" : 208,
            "202375168" : 237,
            "204472320" : 221,
            "206569472" : 214,
            "208666624" : 212,
            "210763776" : 208,
            "212860928" : 215,
            "214958080" : 212,
            "217055232" : 231,
            "219152384" : 224,
            "221249536" : 229,
            "223346688" : 195,
            "225443840" : 203,
            "227540992" : 217,
            "229638144" : 220,
            "231735296" : 209,
            "233832448" : 193,
            "235929600" : 224,
            "238026752" : 227,
            "240123904" : 219,
            "242221056" : 181,
            "244318208" : 211,
            "246415360" : 199,
            "248512512" : 192,
            "250609664" : 196,
            "252706816" : 194,
            "254803968" : 198,
            "256901120" : 189,
            "258998272" : 237,
            "261095424" : 224,
            "263192576" : 206,
            "265289728" : 207,
            "267386880" : 204,
            "270532608" : 393,
            "274726912" : 345,
            "278921216" : 364,
            "283115520" : 351,
            "287309824" : 365,
            "291504128" : 336,
            "295698432" : 343,
            "299892736" : 348,
            "304087040" : 327,
            "308281344" : 321,
            "312475648" : 316,
            "316669952" : 314,
            "320864256" : 326,
            "325058560" : 294,
            "329252864" : 289,
            "333447168" : 308,
            "337641472" : 302,
            "341835776" : 295,
            "346030080" : 314,
            "350224384" : 261,
            "354418688" : 288,
            "358612992" : 243,
            "362807296" : 263,
            "367001600" : 233,
            "371195904" : 281,
            "375390208" : 232,
            "379584512" : 207,
            "383778816" : 211,
            "387973120" : 235,
            "392167424" : 249,
            "396361728" : 233,
            "400556032" : 200,
            "404750336" : 199,
            "408944640" : 199,
            "413138944" : 205,
            "417333248" : 204,
            "421527552" : 214,
            "425721856" : 175,
            "429916160" : 198,
            "434110464" : 167,
            "438304768" : 154,
            "442499072" : 163,
            "446693376" : 146,
            "450887680" : 134,
            "455081984" : 148,
            "459276288" : 136,
            "463470592" : 144,
            "467664896" : 139,
            "471859200" : 117,
            "476053504" : 135,
            "480247808" : 121,
            "484442112" : 129,
            "488636416" : 119,
            "492830720" : 119,
            "497025024" : 129,
            "501219328" : 117,
            "505413632" : 121,
            "509607936" : 113,
            "513802240" : 115,
            "517996544" : 98,
            "522190848" : 91,
            "526385152" : 110,
            "530579456" : 98,
            "534773760" : 87,
            "541065216" : 199,
            "549453824" : 163,
            "557842432" : 170,
            "566231040" : 166,
            "574619648" : 145,
            "583008256" : 136,
            "591396864" : 138,
            "599785472" : 118,
            "608174080" : 107,
            "616562688" : 119,
            "624951296" : 124,
            "633339904" : 100,
            "641728512" : 102,
            "650117120" : 94,
            "658505728" : 82,
            "666894336" : 69,
            "675282944" : 77,
            "683671552" : 78,
            "692060160" : 53,
            "700448768" : 88,
            "708837376" : 82,
            "717225984" : 59,
            "725614592" : 65,
            "734003200" : 60,
            "742391808" : 43,
            "750780416" : 62,
            "759169024" : 54,
            "767557632" : 53,
            "775946240" : 44,
            "784334848" : 41,
            "792723456" : 47,
            "801112064" : 52,
            "809500672" : 36,
            "817889280" : 45,
            "826277888" : 35,
            "834666496" : 38,
            "843055104" : 34,
            "851443712" : 35,
            "859832320" : 34,
            "868220928" : 22,
            "876609536" : 25,
            "884998144" : 22,
            "893386752" : 18,
            "901775360" : 23,
            "910163968" : 25,
            "918552576" : 18,
            "926941184" : 22,
            "935329792" : 17,
            "943718400" : 20,
            "952107008" : 15,
            "960495616" : 13,
            "968884224" : 21,
            "977272832" : 16,
            "985661440" : 15,
            "994050048" : 10,
            "1002438656" : 7,
            "1010827264" : 14,
            "1019215872" : 5,
            "1027604480" : 11,
            "1035993088" : 13,
            "1044381696" : 6,
            "1052770304" : 7,
            "1061158912" : 6,
            "1069547520" : 8,
            "1082130432" : 6,
            "1098907648" : 13,
            "1115684864" : 10,
            "1132462080" : 21,
            "1149239296" : 9,
            "1166016512" : 10,
            "1182793728" : 8,
            "1199570944" : 7,
            "1216348160" : 6,
            "1233125376" : 9,
            "1249902592" : 10,
            "1266679808" : 7,
            "1283457024" : 6,
            "1300234240" : 6,
            "1317011456" : 6,
            "1333788672" : 3,
            "1350565888" : 2,
            "1384120320" : 2,
            "1400897536" : 3,
            "1417674752" : 3,
            "1434451968" : 3,
            "1451229184" : 1,
            "1468006400" : 1,
            "1484783616" : 2,
            "1501560832" : 2,
            "1535115264" : 1,
            "1551892480" : 2,
            "1585446912" : 1,
            "1652555776" : 1,
            "1669332992" : 2,
            "1686110208" : 1,
            "1803550720" : 2,
            "1920991232" : 1,
            "1937768448" : 1,
            "2231369728" : 1,
            "2264924160" : 1,
            "2298478592" : 1,
            "2432696320" : 1
          }
        },
        "lat_ns" : {
          "min" : 7932166,
          "max" : 2432785313,
          "mean" : 275814335.628029,
          "stddev" : 191572509.765067
        },
        "bw_min" : 96063,
        "bw_max" : 137216,
        "bw_agg" : 99.916344,
        "bw_mean" : 118697.619444,
        "bw_dev" : 7230.417136,
        "bw_samples" : 720,
        "iops_min" : 93,
        "iops_max" : 134,
        "iops_mean" : 115.616667,
        "iops_stddev" : 7.102097,
        "iops_samples" : 720
      },
      "write" : {
        "io_bytes" : 0,
        "io_kbytes" : 0,
        "bw_bytes" : 0,
        "bw" : 0,
        "iops" : 0.000000,
        "runtime" : 0,
        "total_ios" : 0,
        "short_ios" : 0,
        "drop_ios" : 0,
        "slat_ns" : {
          "min" : 0,
          "max" : 0,
          "mean" : 0.000000,
          "stddev" : 0.000000
        },
        "clat_ns" : {
          "min" : 0,
          "max" : 0,
          "mean" : 0.000000,
          "stddev" : 0.000000,
          "percentile" : {
            "1.000000" : 0,
            "5.000000" : 0,
            "10.000000" : 0,
            "20.000000" : 0,
            "30.000000" : 0,
            "40.000000" : 0,
            "50.000000" : 0,
            "60.000000" : 0,
            "70.000000" : 0,
            "80.000000" : 0,
            "90.000000" : 0,
            "95.000000" : 0,
            "99.000000" : 0,
            "99.500000" : 0,
            "99.900000" : 0,
            "99.950000" : 0,
            "99.990000" : 0
          },
          "bins" : {

          }
        },
        "lat_ns" : {
          "min" : 0,
          "max" : 0,
          "mean" : 0.000000,
          "stddev" : 0.000000
        },
        "bw_min" : 0,
        "bw_max" : 0,
        "bw_agg" : 0.000000,
        "bw_mean" : 0.000000,
        "bw_dev" : 0.000000,
        "bw_samples" : 0,
        "iops_min" : 0,
        "iops_max" : 0,
        "iops_mean" : 0.000000,
        "iops_stddev" : 0.000000,
        "iops_samples" : 0
      },
      "trim" : {
        "io_bytes" : 0,
        "io_kbytes" : 0,
        "bw_bytes" : 0,
        "bw" : 0,
        "iops" : 0.000000,
        "runtime" : 0,
        "total_ios" : 0,
        "short_ios" : 0,
        "drop_ios" : 0,
        "slat_ns" : {
          "min" : 0,
          "max" : 0,
          "mean" : 0.000000,
          "stddev" : 0.000000
        },
        "clat_ns" : {
          "min" : 0,
          "max" : 0,
          "mean" : 0.000000,
          "stddev" : 0.000000,
          "percentile" : {
            "1.000000" : 0,
            "5.000000" : 0,
            "10.000000" : 0,
            "20.000000" : 0,
            "30.000000" : 0,
            "40.000000" : 0,
            "50.000000" : 0,
            "60.000000" : 0,
            "70.000000" : 0,
            "80.000000" : 0,
            "90.000000" : 0,
            "95.000000" : 0,
            "99.000000" : 0,
            "99.500000" : 0,
            "99.900000" : 0,
            "99.950000" : 0,
            "99.990000" : 0
          },
          "bins" : {

          }
        },
        "lat_ns" : {
          "min" : 0,
          "max" : 0,
          "mean" : 0.000000,
          "stddev" : 0.000000
        },
        "bw_min" : 0,
        "bw_max" : 0,
        "bw_agg" : 0.000000,
        "bw_mean" : 0.000000,
        "bw_dev" : 0.000000,
        "bw_samples" : 0,
        "iops_min" : 0,
        "iops_max" : 0,
        "iops_mean" : 0.000000,
        "iops_stddev" : 0.000000,
        "iops_samples" : 0
      },
      "sync" : {
        "lat_ns" : {
          "min" : 0,
          "max" : 0,
          "mean" : 0.000000,
          "stddev" : 0.000000,
          "percentile" : {
            "1.000000" : 0,
            "5.000000" : 0,
            "10.000000" : 0,
            "20.000000" : 0,
            "30.000000" : 0,
            "40.000000" : 0,
            "50.000000" : 0,
            "60.000000" : 0,
            "70.000000" : 0,
            "80.000000" : 0,
            "90.000000" : 0,
            "95.000000" : 0,
            "99.000000" : 0,
            "99.500000" : 0,
            "99.900000" : 0,
            "99.950000" : 0,
            "99.990000" : 0
          },
          "bins" : {

          }
        },
        "total_ios" : 0
      },
      "usr_cpu" : 0.129354,
      "sys_cpu" : 5.240776,
      "ctx" : 40845,
      "majf" : 0,
      "minf" : 4377,
      "iodepth_level" : {
        "1" : 0.100000,
        "2" : 0.100000,
        "4" : 0.100000,
        "8" : 0.100000,
        "16" : 0.100000,
        "32" : 99.925827,
        ">=64" : 0.000000
      },
      "latency_ns" : {
        "2" : 0.000000,
        "4" : 0.000000,
        "10" : 0.000000,
        "20" : 0.000000,
        "50" : 0.000000,
        "100" : 0.000000,
        "250" : 0.000000,
        "500" : 0.000000,
        "750" : 0.000000,
        "1000" : 0.000000
      },
      "latency_us" : {
        "2" : 0.000000,
        "4" : 0.000000,
        "10" : 0.000000,
        "20" : 0.000000,
        "50" : 0.000000,
        "100" : 0.000000,
        "250" : 0.000000,
        "500" : 0.000000,
        "750" : 0.000000,
        "1000" : 0.000000
      },
      "latency_ms" : {
        "2" : 0.000000,
        "4" : 0.000000,
        "10" : 0.016749,
        "20" : 0.607743,
        "50" : 4.314016,
        "100" : 10.580466,
        "250" : 37.711155,
        "500" : 35.462028,
        "750" : 8.594535,
        "1000" : 2.119922,
        "2000" : 0.000000,
        ">=2000" : 0.000000
      },
      "latency_depth" : 32,
      "latency_target" : 0,
      "latency_percentile" : 100.000000,
      "latency_window" : 0
    }
  ]
}
