{
  "fio version" : "fio-3.7",
  "timestamp" : 1579578693,
  "timestamp_ms" : 1579578693758,
  "time" : "Mon Jan 20 20:51:33 2020",
  "global options" : {
    "directory" : "/tank/"
  },
  "jobs" : [
    {
      "jobname" : "mach2_zfs_zmirror",
      "groupid" : 0,
      "error" : 0,
      "eta" : 0,
      "elapsed" : 181,
      "job options" : {
        "name" : "mach2_zfs_zmirror",
        "rw" : "randwrite",
        "group_reporting" : "1",
        "bs" : "4k",
        "direct" : "1",
        "numjobs" : "8",
        "time_based" : "1",
        "runtime" : "180",
        "iodepth" : "128",
        "ioengine" : "libaio",
        "size" : "64G"
      },
      "read" : {
        "io_bytes" : 0,
        "io_kbytes" : 0,
        "bw_bytes" : 0,
        "bw" : 0,
        "iops" : 0.000000,
        "runtime" : 0,
        "total_ios" : 0,
        "short_ios" : 0,
        "drop_ios" : 0,
        "slat_ns" : {
          "min" : 0,
          "max" : 0,
          "mean" : 0.000000,
          "stddev" : 0.000000
        },
        "clat_ns" : {
          "min" : 0,
          "max" : 0,
          "mean" : 0.000000,
          "stddev" : 0.000000,
          "percentile" : {
            "1.000000" : 0,
            "5.000000" : 0,
            "10.000000" : 0,
            "20.000000" : 0,
            "30.000000" : 0,
            "40.000000" : 0,
            "50.000000" : 0,
            "60.000000" : 0,
            "70.000000" : 0,
            "80.000000" : 0,
            "90.000000" : 0,
            "95.000000" : 0,
            "99.000000" : 0,
            "99.500000" : 0,
            "99.900000" : 0,
            "99.950000" : 0,
            "99.990000" : 0
          }
        },
        "lat_ns" : {
          "min" : 0,
          "max" : 0,
          "mean" : 0.000000,
          "stddev" : 0.000000
        },
        "bw_min" : 0,
        "bw_max" : 0,
        "bw_agg" : 0.000000,
        "bw_mean" : 0.000000,
        "bw_dev" : 0.000000,
        "bw_samples" : 0,
        "iops_min" : 0,
        "iops_max" : 0,
        "iops_mean" : 0.000000,
        "iops_stddev" : 0.000000,
        "iops_samples" : 0
      },
      "write" : {
        "io_bytes" : 943742976,
        "io_kbytes" : 921624,
        "bw_bytes" : 5242637,
        "bw" : 5119,
        "iops" : 1279.940893,
        "runtime" : 180013,
        "total_ios" : 230406,
        "short_ios" : 0,
        "drop_ios" : 0,
        "slat_ns" : {
          "min" : 6183,
          "max" : 395017567,
          "mean" : 6243712.677886,
          "stddev" : 8495692.337427
        },
        "clat_ns" : {
          "min" : 7656,
          "max" : 2369652960,
          "mean" : 790933009.306619,
          "stddev" : 449917527.270284,
          "percentile" : {
            "1.000000" : 13434880,
            "5.000000" : 31850496,
            "10.000000" : 47448064,
            "20.000000" : 115867648,
            "30.000000" : 809500672,
            "40.000000" : 876609536,
            "50.000000" : 926941184,
            "60.000000" : 968884224,
            "70.000000" : 1027604480,
            "80.000000" : 1132462080,
            "90.000000" : 1266679808,
            "95.000000" : 1367343104,
            "99.000000" : 1535115264,
            "99.500000" : 1619001344,
            "99.900000" : 2021654528,
            "99.950000" : 2122317824,
            "99.990000" : 2332033024
          }
        },
        "lat_ns" : {
          "min" : 5898089,
          "max" : 2380124208,
          "mean" : 797177328.928069,
          "stddev" : 453216412.642330
        },
        "bw_min" : 48,
        "bw_max" : 14928,
        "bw_agg" : 12.510043,
        "bw_mean" : 640.389102,
        "bw_dev" : 1041.616018,
        "bw_samples" : 2863,
        "iops_min" : 12,
        "iops_max" : 3732,
        "iops_mean" : 159.988124,
        "iops_stddev" : 260.414078,
        "iops_samples" : 2863
      },
      "trim" : {
        "io_bytes" : 0,
        "io_kbytes" : 0,
        "bw_bytes" : 0,
        "bw" : 0,
        "iops" : 0.000000,
        "runtime" : 0,
        "total_ios" : 0,
        "short_ios" : 0,
        "drop_ios" : 0,
        "slat_ns" : {
          "min" : 0,
          "max" : 0,
          "mean" : 0.000000,
          "stddev" : 0.000000
        },
        "clat_ns" : {
          "min" : 0,
          "max" : 0,
          "mean" : 0.000000,
          "stddev" : 0.000000,
          "percentile" : {
            "1.000000" : 0,
            "5.000000" : 0,
            "10.000000" : 0,
            "20.000000" : 0,
            "30.000000" : 0,
            "40.000000" : 0,
            "50.000000" : 0,
            "60.000000" : 0,
            "70.000000" : 0,
            "80.000000" : 0,
            "90.000000" : 0,
            "95.000000" : 0,
            "99.000000" : 0,
            "99.500000" : 0,
            "99.900000" : 0,
            "99.950000" : 0,
            "99.990000" : 0
          }
        },
        "lat_ns" : {
          "min" : 0,
          "max" : 0,
          "mean" : 0.000000,
          "stddev" : 0.000000
        },
        "bw_min" : 0,
        "bw_max" : 0,
        "bw_agg" : 0.000000,
        "bw_mean" : 0.000000,
        "bw_dev" : 0.000000,
        "bw_samples" : 0,
        "iops_min" : 0,
        "iops_max" : 0,
        "iops_mean" : 0.000000,
        "iops_stddev" : 0.000000,
        "iops_samples" : 0
      },
      "sync" : {
        "lat_ns" : {
          "min" : 0,
          "max" : 0,
          "mean" : 0.000000,
          "stddev" : 0.000000,
          "percentile" : {
            "1.000000" : 0,
            "5.000000" : 0,
            "10.000000" : 0,
            "20.000000" : 0,
            "30.000000" : 0,
            "40.000000" : 0,
            "50.000000" : 0,
            "60.000000" : 0,
            "70.000000" : 0,
            "80.000000" : 0,
            "90.000000" : 0,
            "95.000000" : 0,
            "99.000000" : 0,
            "99.500000" : 0,
            "99.900000" : 0,
            "99.950000" : 0,
            "99.990000" : 0
          }
        },
        "total_ios" : 0
      },
      "usr_cpu" : 0.130344,
      "sys_cpu" : 1.451495,
      "ctx" : 138499,
      "majf" : 0,
      "minf" : 5649,
      "iodepth_level" : {
        "1" : 0.100000,
        "2" : 0.100000,
        "4" : 0.100000,
        "8" : 0.100000,
        "16" : 0.100000,
        "32" : 0.111108,
        ">=64" : 99.781256
      },
      "latency_ns" : {
        "2" : 0.000000,
        "4" : 0.000000,
        "10" : 0.000000,
        "20" : 0.000000,
        "50" : 0.000000,
        "100" : 0.000000,
        "250" : 0.000000,
        "500" : 0.000000,
        "750" : 0.000000,
        "1000" : 0.000000
      },
      "latency_us" : {
        "2" : 0.000000,
        "4" : 0.000000,
        "10" : 0.010000,
        "20" : 0.010000,
        "50" : 0.010000,
        "100" : 0.000000,
        "250" : 0.000000,
        "500" : 0.000000,
        "750" : 0.000000,
        "1000" : 0.000000
      },
      "latency_ms" : {
        "2" : 0.000000,
        "4" : 0.000000,
        "10" : 0.641042,
        "20" : 1.565931,
        "50" : 8.341363,
        "100" : 7.909516,
        "250" : 5.944724,
        "500" : 1.397099,
        "750" : 1.591972,
        "1000" : 37.992066,
        "2000" : 0.000000,
        ">=2000" : 0.000000
      },
      "latency_depth" : 128,
      "latency_target" : 0,
      "latency_percentile" : 100.000000,
      "latency_window" : 0
    }
  ]
}
