{
  "fio version" : "fio-3.7",
  "timestamp" : 1579584390,
  "timestamp_ms" : 1579584390396,
  "time" : "Mon Jan 20 22:26:30 2020",
  "global options" : {
    "directory" : "/tank/"
  },
  "jobs" : [
    {
      "jobname" : "mach2_zfs_zmirror",
      "groupid" : 0,
      "error" : 0,
      "eta" : 0,
      "elapsed" : 181,
      "job options" : {
        "name" : "mach2_zfs_zmirror",
        "rw" : "randrw",
        "group_reporting" : "1",
        "bs" : "16k",
        "direct" : "1",
        "numjobs" : "12",
        "time_based" : "1",
        "runtime" : "180",
        "iodepth" : "128",
        "ioengine" : "libaio",
        "size" : "64G"
      },
      "read" : {
        "io_bytes" : 3050799104,
        "io_kbytes" : 2979296,
        "bw_bytes" : 16947377,
        "bw" : 16550,
        "iops" : 1034.385832,
        "runtime" : 180016,
        "total_ios" : 186206,
        "short_ios" : 0,
        "drop_ios" : 0,
        "slat_ns" : {
          "min" : 5707,
          "max" : 245245910,
          "mean" : 4878439.031943,
          "stddev" : 7900122.072328
        },
        "clat_ns" : {
          "min" : 9488,
          "max" : 2134888100,
          "mean" : 735546245.688758,
          "stddev" : 456972393.326642,
          "percentile" : {
            "1.000000" : 137363456,
            "5.000000" : 185597952,
            "10.000000" : 223346688,
            "20.000000" : 291504128,
            "30.000000" : 358612992,
            "40.000000" : 455081984,
            "50.000000" : 633339904,
            "60.000000" : 809500672,
            "70.000000" : 1061158912,
            "80.000000" : 1233125376,
            "90.000000" : 1400897536,
            "95.000000" : 1518338048,
            "99.000000" : 1719664640,
            "99.500000" : 1786773504,
            "99.900000" : 1904214016,
            "99.950000" : 1954545664,
            "99.990000" : 2055208960
          }
        },
        "lat_ns" : {
          "min" : 7051871,
          "max" : 2147306072,
          "mean" : 740425033.761389,
          "stddev" : 461533823.228932
        },
        "bw_min" : 96,
        "bw_max" : 6848,
        "bw_agg" : 8.299938,
        "bw_mean" : 1373.639731,
        "bw_dev" : 1033.761936,
        "bw_samples" : 4319,
        "iops_min" : 6,
        "iops_max" : 428,
        "iops_mean" : 85.773327,
        "iops_stddev" : 64.638581,
        "iops_samples" : 4319
      },
      "write" : {
        "io_bytes" : 3054206976,
        "io_kbytes" : 2982624,
        "bw_bytes" : 16966308,
        "bw" : 16568,
        "iops" : 1035.541285,
        "runtime" : 180016,
        "total_ios" : 186414,
        "short_ios" : 0,
        "drop_ios" : 0,
        "slat_ns" : {
          "min" : 10033,
          "max" : 236688861,
          "mean" : 6703759.957482,
          "stddev" : 8402883.945595
        },
        "clat_ns" : {
          "min" : 17175,
          "max" : 2134925896,
          "mean" : 734699356.246032,
          "stddev" : 457411169.259854,
          "percentile" : {
            "1.000000" : 137363456,
            "5.000000" : 185597952,
            "10.000000" : 223346688,
            "20.000000" : 291504128,
            "30.000000" : 358612992,
            "40.000000" : 450887680,
            "50.000000" : 624951296,
            "60.000000" : 809500672,
            "70.000000" : 1069547520,
            "80.000000" : 1233125376,
            "90.000000" : 1400897536,
            "95.000000" : 1518338048,
            "99.000000" : 1719664640,
            "99.500000" : 1786773504,
            "99.900000" : 1904214016,
            "99.950000" : 1937768448,
            "99.990000" : 2038431744
          }
        },
        "lat_ns" : {
          "min" : 10247276,
          "max" : 2141808693,
          "mean" : 741403826.705156,
          "stddev" : 459623494.285623
        },
        "bw_min" : 96,
        "bw_max" : 6624,
        "bw_agg" : 8.300759,
        "bw_mean" : 1375.269738,
        "bw_dev" : 1034.352168,
        "bw_samples" : 4319,
        "iops_min" : 6,
        "iops_max" : 414,
        "iops_mean" : 85.875203,
        "iops_stddev" : 64.676452,
        "iops_samples" : 4319
      },
      "trim" : {
        "io_bytes" : 0,
        "io_kbytes" : 0,
        "bw_bytes" : 0,
        "bw" : 0,
        "iops" : 0.000000,
        "runtime" : 0,
        "total_ios" : 0,
        "short_ios" : 0,
        "drop_ios" : 0,
        "slat_ns" : {
          "min" : 0,
          "max" : 0,
          "mean" : 0.000000,
          "stddev" : 0.000000
        },
        "clat_ns" : {
          "min" : 0,
          "max" : 0,
          "mean" : 0.000000,
          "stddev" : 0.000000,
          "percentile" : {
            "1.000000" : 0,
            "5.000000" : 0,
            "10.000000" : 0,
            "20.000000" : 0,
            "30.000000" : 0,
            "40.000000" : 0,
            "50.000000" : 0,
            "60.000000" : 0,
            "70.000000" : 0,
            "80.000000" : 0,
            "90.000000" : 0,
            "95.000000" : 0,
            "99.000000" : 0,
            "99.500000" : 0,
            "99.900000" : 0,
            "99.950000" : 0,
            "99.990000" : 0
          }
        },
        "lat_ns" : {
          "min" : 0,
          "max" : 0,
          "mean" : 0.000000,
          "stddev" : 0.000000
        },
        "bw_min" : 0,
        "bw_max" : 0,
        "bw_agg" : 0.000000,
        "bw_mean" : 0.000000,
        "bw_dev" : 0.000000,
        "bw_samples" : 0,
        "iops_min" : 0,
        "iops_max" : 0,
        "iops_mean" : 0.000000,
        "iops_stddev" : 0.000000,
        "iops_samples" : 0
      },
      "sync" : {
        "lat_ns" : {
          "min" : 0,
          "max" : 0,
          "mean" : 0.000000,
          "stddev" : 0.000000,
          "percentile" : {
            "1.000000" : 0,
            "5.000000" : 0,
            "10.000000" : 0,
            "20.000000" : 0,
            "30.000000" : 0,
            "40.000000" : 0,
            "50.000000" : 0,
            "60.000000" : 0,
            "70.000000" : 0,
            "80.000000" : 0,
            "90.000000" : 0,
            "95.000000" : 0,
            "99.000000" : 0,
            "99.500000" : 0,
            "99.900000" : 0,
            "99.950000" : 0,
            "99.990000" : 0
          }
        },
        "total_ios" : 0
      },
      "usr_cpu" : 0.136245,
      "sys_cpu" : 1.424022,
      "ctx" : 252723,
      "majf" : 0,
      "minf" : 8400,
      "iodepth_level" : {
        "1" : 0.100000,
        "2" : 0.100000,
        "4" : 0.100000,
        "8" : 0.100000,
        "16" : 0.100000,
        "32" : 0.103054,
        ">=64" : 99.797112
      },
      "latency_ns" : {
        "2" : 0.000000,
        "4" : 0.000000,
        "10" : 0.000000,
        "20" : 0.000000,
        "50" : 0.000000,
        "100" : 0.000000,
        "250" : 0.000000,
        "500" : 0.000000,
        "750" : 0.000000,
        "1000" : 0.000000
      },
      "latency_us" : {
        "2" : 0.000000,
        "4" : 0.000000,
        "10" : 0.010000,
        "20" : 0.010000,
        "50" : 0.010000,
        "100" : 0.000000,
        "250" : 0.000000,
        "500" : 0.000000,
        "750" : 0.000000,
        "1000" : 0.000000
      },
      "latency_ms" : {
        "2" : 0.000000,
        "4" : 0.000000,
        "10" : 0.010000,
        "20" : 0.010000,
        "50" : 0.010198,
        "100" : 0.170147,
        "250" : 13.765498,
        "500" : 29.644947,
        "750" : 12.761526,
        "1000" : 12.201438,
        "2000" : 0.000000,
        ">=2000" : 0.000000
      },
      "latency_depth" : 128,
      "latency_target" : 0,
      "latency_percentile" : 100.000000,
      "latency_window" : 0
    }
  ]
}
