{
  "fio version" : "fio-3.7",
  "timestamp" : 1579614645,
  "timestamp_ms" : 1579614645476,
  "time" : "Tue Jan 21 06:50:45 2020",
  "global options" : {
    "directory" : "/tank/"
  },
  "jobs" : [
    {
      "jobname" : "mach2_zfs_raidz1",
      "groupid" : 0,
      "error" : 0,
      "eta" : 0,
      "elapsed" : 181,
      "job options" : {
        "name" : "mach2_zfs_raidz1",
        "rw" : "randread",
        "group_reporting" : "1",
        "bs" : "1M",
        "direct" : "1",
        "numjobs" : "28",
        "time_based" : "1",
        "runtime" : "180",
        "iodepth" : "128",
        "ioengine" : "libaio",
        "size" : "64G"
      },
      "read" : {
        "io_bytes" : 109139984384,
        "io_kbytes" : 106582016,
        "bw_bytes" : 606070615,
        "bw" : 591865,
        "iops" : 577.993980,
        "runtime" : 180078,
        "total_ios" : 104084,
        "short_ios" : 0,
        "drop_ios" : 0,
        "slat_ns" : {
          "min" : 411019,
          "max" : 602546881,
          "mean" : 48421907.162350,
          "stddev" : 36563444.846234
        },
        "clat_ns" : {
          "min" : 9640,
          "max" : 10671118305,
          "mean" : 6047554684.620720,
          "stddev" : 1417332249.887328,
          "percentile" : {
            "1.000000" : 2399141888,
            "5.000000" : 4211081216,
            "10.000000" : 4462739456,
            "20.000000" : 4865392640,
            "30.000000" : 5133828096,
            "40.000000" : 5402263552,
            "50.000000" : 5804916736,
            "60.000000" : 6408896512,
            "70.000000" : 6945767424,
            "80.000000" : 7482638336,
            "90.000000" : 7952400384,
            "95.000000" : 8287944704,
            "99.000000" : 8925478912,
            "99.500000" : 9328132096,
            "99.900000" : 9999220736,
            "99.950000" : 10133438464,
            "99.990000" : 10536091648
          }
        },
        "lat_ns" : {
          "min" : 34201842,
          "max" : 10750974820,
          "mean" : 6095977855.894749,
          "stddev" : 1425113577.698395
        },
        "bw_min" : 2048,
        "bw_max" : 45056,
        "bw_agg" : 3.565053,
        "bw_mean" : 21100.299498,
        "bw_dev" : 6593.455775,
        "bw_samples" : 9753,
        "iops_min" : 2,
        "iops_max" : 44,
        "iops_mean" : 20.530606,
        "iops_stddev" : 6.443666,
        "iops_samples" : 9753
      },
      "write" : {
        "io_bytes" : 0,
        "io_kbytes" : 0,
        "bw_bytes" : 0,
        "bw" : 0,
        "iops" : 0.000000,
        "runtime" : 0,
        "total_ios" : 0,
        "short_ios" : 0,
        "drop_ios" : 0,
        "slat_ns" : {
          "min" : 0,
          "max" : 0,
          "mean" : 0.000000,
          "stddev" : 0.000000
        },
        "clat_ns" : {
          "min" : 0,
          "max" : 0,
          "mean" : 0.000000,
          "stddev" : 0.000000,
          "percentile" : {
            "1.000000" : 0,
            "5.000000" : 0,
            "10.000000" : 0,
            "20.000000" : 0,
            "30.000000" : 0,
            "40.000000" : 0,
            "50.000000" : 0,
            "60.000000" : 0,
            "70.000000" : 0,
            "80.000000" : 0,
            "90.000000" : 0,
            "95.000000" : 0,
            "99.000000" : 0,
            "99.500000" : 0,
            "99.900000" : 0,
            "99.950000" : 0,
            "99.990000" : 0
          }
        },
        "lat_ns" : {
          "min" : 0,
          "max" : 0,
          "mean" : 0.000000,
          "stddev" : 0.000000
        },
        "bw_min" : 0,
        "bw_max" : 0,
        "bw_agg" : 0.000000,
        "bw_mean" : 0.000000,
        "bw_dev" : 0.000000,
        "bw_samples" : 0,
        "iops_min" : 0,
        "iops_max" : 0,
        "iops_mean" : 0.000000,
        "iops_stddev" : 0.000000,
        "iops_samples" : 0
      },
      "trim" : {
        "io_bytes" : 0,
        "io_kbytes" : 0,
        "bw_bytes" : 0,
        "bw" : 0,
        "iops" : 0.000000,
        "runtime" : 0,
        "total_ios" : 0,
        "short_ios" : 0,
        "drop_ios" : 0,
        "slat_ns" : {
          "min" : 0,
          "max" : 0,
          "mean" : 0.000000,
          "stddev" : 0.000000
        },
        "clat_ns" : {
          "min" : 0,
          "max" : 0,
          "mean" : 0.000000,
          "stddev" : 0.000000,
          "percentile" : {
            "1.000000" : 0,
            "5.000000" : 0,
            "10.000000" : 0,
            "20.000000" : 0,
            "30.000000" : 0,
            "40.000000" : 0,
            "50.000000" : 0,
            "60.000000" : 0,
            "70.000000" : 0,
            "80.000000" : 0,
            "90.000000" : 0,
            "95.000000" : 0,
            "99.000000" : 0,
            "99.500000" : 0,
            "99.900000" : 0,
            "99.950000" : 0,
            "99.990000" : 0
          }
        },
        "lat_ns" : {
          "min" : 0,
          "max" : 0,
          "mean" : 0.000000,
          "stddev" : 0.000000
        },
        "bw_min" : 0,
        "bw_max" : 0,
        "bw_agg" : 0.000000,
        "bw_mean" : 0.000000,
        "bw_dev" : 0.000000,
        "bw_samples" : 0,
        "iops_min" : 0,
        "iops_max" : 0,
        "iops_mean" : 0.000000,
        "iops_stddev" : 0.000000,
        "iops_samples" : 0
      },
      "sync" : {
        "lat_ns" : {
          "min" : 0,
          "max" : 0,
          "mean" : 0.000000,
          "stddev" : 0.000000,
          "percentile" : {
            "1.000000" : 0,
            "5.000000" : 0,
            "10.000000" : 0,
            "20.000000" : 0,
            "30.000000" : 0,
            "40.000000" : 0,
            "50.000000" : 0,
            "60.000000" : 0,
            "70.000000" : 0,
            "80.000000" : 0,
            "90.000000" : 0,
            "95.000000" : 0,
            "99.000000" : 0,
            "99.500000" : 0,
            "99.900000" : 0,
            "99.950000" : 0,
            "99.990000" : 0
          }
        },
        "total_ios" : 0
      },
      "usr_cpu" : 0.020294,
      "sys_cpu" : 1.425294,
      "ctx" : 104603,
      "majf" : 127,
      "minf" : 1837019,
      "iodepth_level" : {
        "1" : 0.100000,
        "2" : 0.100000,
        "4" : 0.107605,
        "8" : 0.215211,
        "16" : 0.430422,
        "32" : 0.860843,
        ">=64" : 98.305215
      },
      "latency_ns" : {
        "2" : 0.000000,
        "4" : 0.000000,
        "10" : 0.000000,
        "20" : 0.000000,
        "50" : 0.000000,
        "100" : 0.000000,
        "250" : 0.000000,
        "500" : 0.000000,
        "750" : 0.000000,
        "1000" : 0.000000
      },
      "latency_us" : {
        "2" : 0.000000,
        "4" : 0.000000,
        "10" : 0.010000,
        "20" : 0.024980,
        "50" : 0.000000,
        "100" : 0.000000,
        "250" : 0.000000,
        "500" : 0.000000,
        "750" : 0.000000,
        "1000" : 0.000000
      },
      "latency_ms" : {
        "2" : 0.000000,
        "4" : 0.000000,
        "10" : 0.000000,
        "20" : 0.000000,
        "50" : 0.010000,
        "100" : 0.022098,
        "250" : 0.060528,
        "500" : 0.113370,
        "750" : 0.086469,
        "1000" : 0.109527,
        "2000" : 0.000000,
        ">=2000" : 0.000000
      },
      "latency_depth" : 128,
      "latency_target" : 0,
      "latency_percentile" : 100.000000,
      "latency_window" : 0
    }
  ]
}
