{
  "fio version" : "fio-3.7",
  "timestamp" : 1580327291,
  "timestamp_ms" : 1580327291667,
  "time" : "Wed Jan 29 12:48:11 2020",
  "global options" : {
    "filename" : "/dev/md/MD-001-sda-sdb",
    "direct" : "1",
    "rw" : "randrw",
    "ioengine" : "libaio",
    "iodepth" : "32",
    "numjobs" : "1",
    "runtime" : "360"
  },
  "jobs" : [
    {
      "jobname" : "direct-randrw-4k",
      "groupid" : 0,
      "error" : 0,
      "eta" : 0,
      "elapsed" : 361,
      "job options" : {
        "name" : "direct-randrw-4k",
        "bs" : "4k"
      },
      "read" : {
        "io_bytes" : 202043392,
        "io_kbytes" : 197308,
        "bw_bytes" : 560994,
        "bw" : 547,
        "iops" : 136.961616,
        "runtime" : 360152,
        "total_ios" : 49327,
        "short_ios" : 0,
        "drop_ios" : 0,
        "slat_ns" : {
          "min" : 3401,
          "max" : 154969,
          "mean" : 27497.882539,
          "stddev" : 5985.048963
        },
        "clat_ns" : {
          "min" : 2249728,
          "max" : 1080844185,
          "mean" : 85781908.444827,
          "stddev" : 85757266.214727,
          "percentile" : {
            "1.000000" : 5799936,
            "5.000000" : 8978432,
            "10.000000" : 12517376,
            "20.000000" : 19791872,
            "30.000000" : 30277632,
            "40.000000" : 43253760,
            "50.000000" : 58982400,
            "60.000000" : 78118912,
            "70.000000" : 103284736,
            "80.000000" : 137363456,
            "90.000000" : 193986560,
            "95.000000" : 252706816,
            "99.000000" : 396361728,
            "99.500000" : 471859200,
            "99.900000" : 658505728,
            "99.950000" : 734003200,
            "99.990000" : 918552576
          },
          "bins" : {
            "2244608" : 1,
            "2506752" : 1,
            "2539520" : 1,
            "2572288" : 2,
            "2637824" : 1,
            "2801664" : 3,
            "2965504" : 1,
            "3096576" : 2,
            "3162112" : 2,
            "3194880" : 3,
            "3227648" : 1,
            "3260416" : 1,
            "3358720" : 2,
            "3391488" : 2,
            "3424256" : 6,
            "3457024" : 3,
            "3489792" : 2,
            "3522560" : 3,
            "3555328" : 3,
            "3588096" : 3,
            "3620864" : 3,
            "3653632" : 3,
            "3686400" : 1,
            "3719168" : 5,
            "3751936" : 2,
            "3784704" : 3,
            "3817472" : 3,
            "3850240" : 2,
            "3883008" : 2,
            "3915776" : 1,
            "3948544" : 4,
            "3981312" : 5,
            "4014080" : 5,
            "4046848" : 3,
            "4079616" : 6,
            "4112384" : 2,
            "4145152" : 6,
            "4177920" : 2,
            "4227072" : 9,
            "4292608" : 10,
            "4358144" : 13,
            "4423680" : 11,
            "4489216" : 17,
            "4554752" : 11,
            "4620288" : 12,
            "4685824" : 16,
            "4751360" : 14,
            "4816896" : 16,
            "4882432" : 8,
            "4947968" : 16,
            "5013504" : 11,
            "5079040" : 19,
            "5144576" : 14,
            "5210112" : 23,
            "5275648" : 18,
            "5341184" : 19,
            "5406720" : 19,
            "5472256" : 30,
            "5537792" : 15,
            "5603328" : 22,
            "5668864" : 20,
            "5734400" : 23,
            "5799936" : 25,
            "5865472" : 12,
            "5931008" : 26,
            "5996544" : 25,
            "6062080" : 34,
            "6127616" : 25,
            "6193152" : 30,
            "6258688" : 31,
            "6324224" : 27,
            "6389760" : 18,
            "6455296" : 30,
            "6520832" : 28,
            "6586368" : 32,
            "6651904" : 49,
            "6717440" : 31,
            "6782976" : 42,
            "6848512" : 27,
            "6914048" : 43,
            "6979584" : 36,
            "7045120" : 42,
            "7110656" : 44,
            "7176192" : 55,
            "7241728" : 37,
            "7307264" : 42,
            "7372800" : 40,
            "7438336" : 44,
            "7503872" : 52,
            "7569408" : 54,
            "7634944" : 46,
            "7700480" : 56,
            "7766016" : 51,
            "7831552" : 49,
            "7897088" : 47,
            "7962624" : 43,
            "8028160" : 59,
            "8093696" : 50,
            "8159232" : 48,
            "8224768" : 48,
            "8290304" : 56,
            "8355840" : 36,
            "8454144" : 102,
            "8585216" : 91,
            "8716288" : 95,
            "8847360" : 94,
            "8978432" : 101,
            "9109504" : 93,
            "9240576" : 86,
            "9371648" : 90,
            "9502720" : 77,
            "9633792" : 86,
            "9764864" : 97,
            "9895936" : 80,
            "10027008" : 95,
            "10158080" : 91,
            "10289152" : 92,
            "10420224" : 88,
            "10551296" : 76,
            "10682368" : 92,
            "10813440" : 93,
            "10944512" : 84,
            "11075584" : 114,
            "11206656" : 86,
            "11337728" : 80,
            "11468800" : 106,
            "11599872" : 84,
            "11730944" : 81,
            "11862016" : 97,
            "11993088" : 90,
            "12124160" : 103,
            "12255232" : 85,
            "12386304" : 91,
            "12517376" : 88,
            "12648448" : 87,
            "12779520" : 90,
            "12910592" : 100,
            "13041664" : 101,
            "13172736" : 93,
            "13303808" : 85,
            "13434880" : 95,
            "13565952" : 106,
            "13697024" : 90,
            "13828096" : 99,
            "13959168" : 85,
            "14090240" : 108,
            "14221312" : 116,
            "14352384" : 95,
            "14483456" : 95,
            "14614528" : 96,
            "14745600" : 99,
            "14876672" : 82,
            "15007744" : 105,
            "15138816" : 90,
            "15269888" : 107,
            "15400960" : 83,
            "15532032" : 109,
            "15663104" : 95,
            "15794176" : 83,
            "15925248" : 91,
            "16056320" : 87,
            "16187392" : 83,
            "16318464" : 76,
            "16449536" : 96,
            "16580608" : 87,
            "16711680" : 115,
            "16908288" : 170,
            "17170432" : 173,
            "17432576" : 157,
            "17694720" : 198,
            "17956864" : 158,
            "18219008" : 160,
            "18481152" : 163,
            "18743296" : 153,
            "19005440" : 139,
            "19267584" : 152,
            "19529728" : 137,
            "19791872" : 154,
            "20054016" : 153,
            "20316160" : 151,
            "20578304" : 136,
            "20840448" : 107,
            "21102592" : 114,
            "21364736" : 129,
            "21626880" : 130,
            "21889024" : 115,
            "22151168" : 126,
            "22413312" : 128,
            "22675456" : 132,
            "22937600" : 129,
            "23199744" : 129,
            "23461888" : 134,
            "23724032" : 152,
            "23986176" : 145,
            "24248320" : 132,
            "24510464" : 143,
            "24772608" : 130,
            "25034752" : 143,
            "25296896" : 124,
            "25559040" : 136,
            "25821184" : 129,
            "26083328" : 118,
            "26345472" : 111,
            "26607616" : 149,
            "26869760" : 122,
            "27131904" : 110,
            "27394048" : 121,
            "27656192" : 116,
            "27918336" : 124,
            "28180480" : 98,
            "28442624" : 117,
            "28704768" : 94,
            "28966912" : 116,
            "29229056" : 114,
            "29491200" : 111,
            "29753344" : 121,
            "30015488" : 100,
            "30277632" : 113,
            "30539776" : 120,
            "30801920" : 112,
            "31064064" : 94,
            "31326208" : 109,
            "31588352" : 94,
            "31850496" : 123,
            "32112640" : 109,
            "32374784" : 79,
            "32636928" : 98,
            "32899072" : 95,
            "33161216" : 104,
            "33423360" : 89,
            "33816576" : 224,
            "34340864" : 221,
            "34865152" : 222,
            "35389440" : 239,
            "35913728" : 232,
            "36438016" : 186,
            "36962304" : 198,
            "37486592" : 204,
            "38010880" : 174,
            "38535168" : 198,
            "39059456" : 184,
            "39583744" : 192,
            "40108032" : 179,
            "40632320" : 206,
            "41156608" : 162,
            "41680896" : 175,
            "42205184" : 179,
            "42729472" : 199,
            "43253760" : 157,
            "43778048" : 216,
            "44302336" : 192,
            "44826624" : 175,
            "45350912" : 164,
            "45875200" : 178,
            "46399488" : 167,
            "46923776" : 192,
            "47448064" : 172,
            "47972352" : 178,
            "48496640" : 147,
            "49020928" : 145,
            "49545216" : 162,
            "50069504" : 183,
            "50593792" : 143,
            "51118080" : 151,
            "51642368" : 194,
            "52166656" : 158,
            "52690944" : 193,
            "53215232" : 188,
            "53739520" : 166,
            "54263808" : 159,
            "54788096" : 160,
            "55312384" : 157,
            "55836672" : 144,
            "56360960" : 157,
            "56885248" : 138,
            "57409536" : 144,
            "57933824" : 117,
            "58458112" : 152,
            "58982400" : 139,
            "59506688" : 142,
            "60030976" : 145,
            "60555264" : 167,
            "61079552" : 115,
            "61603840" : 160,
            "62128128" : 149,
            "62652416" : 143,
            "63176704" : 149,
            "63700992" : 136,
            "64225280" : 136,
            "64749568" : 119,
            "65273856" : 149,
            "65798144" : 115,
            "66322432" : 110,
            "66846720" : 121,
            "67633152" : 262,
            "68681728" : 269,
            "69730304" : 283,
            "70778880" : 257,
            "71827456" : 269,
            "72876032" : 257,
            "73924608" : 246,
            "74973184" : 236,
            "76021760" : 249,
            "77070336" : 257,
            "78118912" : 252,
            "79167488" : 231,
            "80216064" : 238,
            "81264640" : 241,
            "82313216" : 217,
            "83361792" : 219,
            "84410368" : 229,
            "85458944" : 237,
            "86507520" : 238,
            "87556096" : 203,
            "88604672" : 226,
            "89653248" : 199,
            "90701824" : 180,
            "91750400" : 220,
            "92798976" : 210,
            "93847552" : 219,
            "94896128" : 214,
            "95944704" : 190,
            "96993280" : 187,
            "98041856" : 187,
            "99090432" : 191,
            "100139008" : 165,
            "101187584" : 171,
            "102236160" : 202,
            "103284736" : 180,
            "104333312" : 191,
            "105381888" : 185,
            "106430464" : 181,
            "107479040" : 177,
            "108527616" : 171,
            "109576192" : 158,
            "110624768" : 151,
            "111673344" : 161,
            "112721920" : 158,
            "113770496" : 161,
            "114819072" : 160,
            "115867648" : 149,
            "116916224" : 180,
            "117964800" : 154,
            "119013376" : 161,
            "120061952" : 149,
            "121110528" : 129,
            "122159104" : 157,
            "123207680" : 145,
            "124256256" : 139,
            "125304832" : 137,
            "126353408" : 157,
            "127401984" : 136,
            "128450560" : 118,
            "129499136" : 137,
            "130547712" : 138,
            "131596288" : 141,
            "132644864" : 138,
            "133693440" : 120,
            "135266304" : 270,
            "137363456" : 225,
            "139460608" : 261,
            "141557760" : 220,
            "143654912" : 228,
            "145752064" : 240,
            "147849216" : 214,
            "149946368" : 219,
            "152043520" : 205,
            "154140672" : 212,
            "156237824" : 213,
            "158334976" : 193,
            "160432128" : 217,
            "162529280" : 178,
            "164626432" : 189,
            "166723584" : 151,
            "168820736" : 177,
            "170917888" : 170,
            "173015040" : 163,
            "175112192" : 141,
            "177209344" : 168,
            "179306496" : 147,
            "181403648" : 138,
            "183500800" : 113,
            "185597952" : 142,
            "187695104" : 159,
            "189792256" : 140,
            "191889408" : 133,
            "193986560" : 129,
            "196083712" : 109,
            "198180864" : 120,
            "200278016" : 116,
            "202375168" : 108,
            "204472320" : 124,
            "206569472" : 115,
            "208666624" : 113,
            "210763776" : 99,
            "212860928" : 100,
            "214958080" : 87,
            "217055232" : 84,
            "219152384" : 102,
            "221249536" : 82,
            "223346688" : 90,
            "225443840" : 79,
            "227540992" : 71,
            "229638144" : 85,
            "231735296" : 83,
            "233832448" : 59,
            "235929600" : 75,
            "238026752" : 74,
            "240123904" : 60,
            "242221056" : 74,
            "244318208" : 64,
            "246415360" : 58,
            "248512512" : 73,
            "250609664" : 46,
            "252706816" : 62,
            "254803968" : 65,
            "256901120" : 48,
            "258998272" : 47,
            "261095424" : 67,
            "263192576" : 60,
            "265289728" : 46,
            "267386880" : 51,
            "270532608" : 96,
            "274726912" : 99,
            "278921216" : 93,
            "283115520" : 91,
            "287309824" : 66,
            "291504128" : 77,
            "295698432" : 73,
            "299892736" : 57,
            "304087040" : 75,
            "308281344" : 59,
            "312475648" : 62,
            "316669952" : 47,
            "320864256" : 60,
            "325058560" : 52,
            "329252864" : 71,
            "333447168" : 36,
            "337641472" : 31,
            "341835776" : 34,
            "346030080" : 44,
            "350224384" : 33,
            "354418688" : 31,
            "358612992" : 40,
            "362807296" : 31,
            "367001600" : 28,
            "371195904" : 31,
            "375390208" : 23,
            "379584512" : 32,
            "383778816" : 24,
            "387973120" : 26,
            "392167424" : 18,
            "396361728" : 20,
            "400556032" : 20,
            "404750336" : 26,
            "408944640" : 5,
            "413138944" : 24,
            "417333248" : 21,
            "421527552" : 22,
            "425721856" : 18,
            "429916160" : 11,
            "434110464" : 12,
            "438304768" : 17,
            "442499072" : 14,
            "446693376" : 9,
            "450887680" : 9,
            "455081984" : 12,
            "459276288" : 9,
            "463470592" : 4,
            "467664896" : 12,
            "471859200" : 5,
            "476053504" : 15,
            "480247808" : 9,
            "484442112" : 14,
            "488636416" : 5,
            "492830720" : 10,
            "497025024" : 5,
            "501219328" : 9,
            "505413632" : 6,
            "509607936" : 7,
            "513802240" : 5,
            "517996544" : 6,
            "522190848" : 3,
            "526385152" : 6,
            "530579456" : 4,
            "534773760" : 4,
            "541065216" : 8,
            "549453824" : 11,
            "557842432" : 12,
            "566231040" : 6,
            "574619648" : 14,
            "583008256" : 5,
            "591396864" : 5,
            "599785472" : 5,
            "608174080" : 2,
            "616562688" : 5,
            "624951296" : 2,
            "633339904" : 5,
            "641728512" : 1,
            "650117120" : 2,
            "658505728" : 6,
            "666894336" : 2,
            "675282944" : 4,
            "683671552" : 1,
            "692060160" : 5,
            "700448768" : 2,
            "708837376" : 1,
            "717225984" : 2,
            "725614592" : 1,
            "734003200" : 4,
            "742391808" : 1,
            "750780416" : 1,
            "759169024" : 2,
            "775946240" : 1,
            "792723456" : 1,
            "801112064" : 1,
            "817889280" : 1,
            "826277888" : 1,
            "834666496" : 1,
            "859832320" : 1,
            "868220928" : 1,
            "884998144" : 1,
            "893386752" : 2,
            "910163968" : 2,
            "918552576" : 2,
            "926941184" : 2,
            "985661440" : 1,
            "1082130432" : 1
          }
        },
        "lat_ns" : {
          "min" : 2279313,
          "max" : 1080858952,
          "mean" : 85810091.614409,
          "stddev" : 85757267.218567
        },
        "bw_min" : 384,
        "bw_max" : 736,
        "bw_agg" : 100.000000,
        "bw_mean" : 547.470833,
        "bw_dev" : 56.533169,
        "bw_samples" : 720,
        "iops_min" : 96,
        "iops_max" : 184,
        "iops_mean" : 136.729167,
        "iops_stddev" : 14.163863,
        "iops_samples" : 720
      },
      "write" : {
        "io_bytes" : 200777728,
        "io_kbytes" : 196072,
        "bw_bytes" : 557480,
        "bw" : 544,
        "iops" : 136.103645,
        "runtime" : 360152,
        "total_ios" : 49018,
        "short_ios" : 0,
        "drop_ios" : 0,
        "slat_ns" : {
          "min" : 2944,
          "max" : 157164,
          "mean" : 28503.436982,
          "stddev" : 6173.622726
        },
        "clat_ns" : {
          "min" : 2840232,
          "max" : 1581031832,
          "mean" : 148692636.177079,
          "stddev" : 144356601.895285,
          "percentile" : {
            "1.000000" : 7372800,
            "5.000000" : 13172736,
            "10.000000" : 19791872,
            "20.000000" : 36438016,
            "30.000000" : 56360960,
            "40.000000" : 79167488,
            "50.000000" : 105381888,
            "60.000000" : 137363456,
            "70.000000" : 177209344,
            "80.000000" : 233832448,
            "90.000000" : 333447168,
            "95.000000" : 434110464,
            "99.000000" : 675282944,
            "99.500000" : 775946240,
            "99.900000" : 1027604480,
            "99.950000" : 1166016512,
            "99.990000" : 1451229184
          },
          "bins" : {
            "2834432" : 1,
            "2899968" : 1,
            "3129344" : 2,
            "3194880" : 1,
            "3457024" : 1,
            "3522560" : 1,
            "3620864" : 1,
            "3784704" : 1,
            "3817472" : 1,
            "3915776" : 1,
            "3981312" : 1,
            "4014080" : 4,
            "4046848" : 1,
            "4112384" : 2,
            "4177920" : 3,
            "4227072" : 5,
            "4292608" : 4,
            "4423680" : 2,
            "4489216" : 3,
            "4620288" : 5,
            "4685824" : 7,
            "4751360" : 2,
            "4816896" : 5,
            "4882432" : 4,
            "4947968" : 4,
            "5013504" : 4,
            "5079040" : 4,
            "5144576" : 11,
            "5210112" : 8,
            "5275648" : 8,
            "5341184" : 6,
            "5406720" : 6,
            "5472256" : 8,
            "5537792" : 7,
            "5603328" : 7,
            "5668864" : 7,
            "5734400" : 4,
            "5799936" : 10,
            "5865472" : 16,
            "5931008" : 9,
            "5996544" : 7,
            "6062080" : 11,
            "6127616" : 7,
            "6193152" : 11,
            "6258688" : 13,
            "6324224" : 7,
            "6389760" : 14,
            "6455296" : 11,
            "6520832" : 19,
            "6586368" : 17,
            "6651904" : 17,
            "6717440" : 16,
            "6782976" : 20,
            "6848512" : 13,
            "6914048" : 14,
            "6979584" : 17,
            "7045120" : 23,
            "7110656" : 20,
            "7176192" : 17,
            "7241728" : 9,
            "7307264" : 15,
            "7372800" : 20,
            "7438336" : 18,
            "7503872" : 11,
            "7569408" : 19,
            "7634944" : 12,
            "7700480" : 23,
            "7766016" : 20,
            "7831552" : 18,
            "7897088" : 17,
            "7962624" : 22,
            "8028160" : 24,
            "8093696" : 26,
            "8159232" : 27,
            "8224768" : 25,
            "8290304" : 33,
            "8355840" : 20,
            "8454144" : 51,
            "8585216" : 50,
            "8716288" : 53,
            "8847360" : 49,
            "8978432" : 48,
            "9109504" : 41,
            "9240576" : 48,
            "9371648" : 42,
            "9502720" : 41,
            "9633792" : 37,
            "9764864" : 43,
            "9895936" : 45,
            "10027008" : 43,
            "10158080" : 51,
            "10289152" : 50,
            "10420224" : 43,
            "10551296" : 35,
            "10682368" : 29,
            "10813440" : 42,
            "10944512" : 37,
            "11075584" : 38,
            "11206656" : 37,
            "11337728" : 47,
            "11468800" : 47,
            "11599872" : 43,
            "11730944" : 41,
            "11862016" : 43,
            "11993088" : 54,
            "12124160" : 54,
            "12255232" : 37,
            "12386304" : 47,
            "12517376" : 52,
            "12648448" : 48,
            "12779520" : 56,
            "12910592" : 41,
            "13041664" : 45,
            "13172736" : 42,
            "13303808" : 52,
            "13434880" : 51,
            "13565952" : 49,
            "13697024" : 54,
            "13828096" : 62,
            "13959168" : 55,
            "14090240" : 63,
            "14221312" : 62,
            "14352384" : 56,
            "14483456" : 57,
            "14614528" : 43,
            "14745600" : 48,
            "14876672" : 45,
            "15007744" : 47,
            "15138816" : 66,
            "15269888" : 47,
            "15400960" : 54,
            "15532032" : 58,
            "15663104" : 47,
            "15794176" : 46,
            "15925248" : 50,
            "16056320" : 49,
            "16187392" : 55,
            "16318464" : 49,
            "16449536" : 56,
            "16580608" : 58,
            "16711680" : 54,
            "16908288" : 94,
            "17170432" : 89,
            "17432576" : 91,
            "17694720" : 105,
            "17956864" : 112,
            "18219008" : 91,
            "18481152" : 93,
            "18743296" : 78,
            "19005440" : 86,
            "19267584" : 75,
            "19529728" : 71,
            "19791872" : 79,
            "20054016" : 89,
            "20316160" : 83,
            "20578304" : 76,
            "20840448" : 74,
            "21102592" : 75,
            "21364736" : 82,
            "21626880" : 78,
            "21889024" : 76,
            "22151168" : 91,
            "22413312" : 80,
            "22675456" : 78,
            "22937600" : 88,
            "23199744" : 102,
            "23461888" : 66,
            "23724032" : 92,
            "23986176" : 86,
            "24248320" : 89,
            "24510464" : 87,
            "24772608" : 85,
            "25034752" : 83,
            "25296896" : 86,
            "25559040" : 80,
            "25821184" : 86,
            "26083328" : 89,
            "26345472" : 71,
            "26607616" : 81,
            "26869760" : 91,
            "27131904" : 81,
            "27394048" : 76,
            "27656192" : 89,
            "27918336" : 81,
            "28180480" : 75,
            "28442624" : 67,
            "28704768" : 83,
            "28966912" : 73,
            "29229056" : 81,
            "29491200" : 68,
            "29753344" : 75,
            "30015488" : 63,
            "30277632" : 80,
            "30539776" : 72,
            "30801920" : 75,
            "31064064" : 62,
            "31326208" : 69,
            "31588352" : 65,
            "31850496" : 83,
            "32112640" : 72,
            "32374784" : 76,
            "32636928" : 72,
            "32899072" : 66,
            "33161216" : 76,
            "33423360" : 73,
            "33816576" : 142,
            "34340864" : 134,
            "34865152" : 141,
            "35389440" : 128,
            "35913728" : 144,
            "36438016" : 138,
            "36962304" : 132,
            "37486592" : 136,
            "38010880" : 123,
            "38535168" : 115,
            "39059456" : 131,
            "39583744" : 141,
            "40108032" : 145,
            "40632320" : 150,
            "41156608" : 124,
            "41680896" : 134,
            "42205184" : 134,
            "42729472" : 152,
            "43253760" : 124,
            "43778048" : 135,
            "44302336" : 133,
            "44826624" : 128,
            "45350912" : 126,
            "45875200" : 123,
            "46399488" : 126,
            "46923776" : 124,
            "47448064" : 138,
            "47972352" : 131,
            "48496640" : 129,
            "49020928" : 125,
            "49545216" : 122,
            "50069504" : 107,
            "50593792" : 123,
            "51118080" : 136,
            "51642368" : 125,
            "52166656" : 123,
            "52690944" : 159,
            "53215232" : 134,
            "53739520" : 132,
            "54263808" : 109,
            "54788096" : 118,
            "55312384" : 114,
            "55836672" : 122,
            "56360960" : 118,
            "56885248" : 144,
            "57409536" : 107,
            "57933824" : 106,
            "58458112" : 125,
            "58982400" : 118,
            "59506688" : 120,
            "60030976" : 102,
            "60555264" : 135,
            "61079552" : 111,
            "61603840" : 119,
            "62128128" : 118,
            "62652416" : 127,
            "63176704" : 106,
            "63700992" : 118,
            "64225280" : 105,
            "64749568" : 106,
            "65273856" : 110,
            "65798144" : 125,
            "66322432" : 95,
            "66846720" : 127,
            "67633152" : 236,
            "68681728" : 209,
            "69730304" : 216,
            "70778880" : 221,
            "71827456" : 219,
            "72876032" : 212,
            "73924608" : 201,
            "74973184" : 208,
            "76021760" : 231,
            "77070336" : 205,
            "78118912" : 219,
            "79167488" : 198,
            "80216064" : 209,
            "81264640" : 197,
            "82313216" : 213,
            "83361792" : 208,
            "84410368" : 190,
            "85458944" : 194,
            "86507520" : 213,
            "87556096" : 207,
            "88604672" : 216,
            "89653248" : 199,
            "90701824" : 188,
            "91750400" : 175,
            "92798976" : 197,
            "93847552" : 196,
            "94896128" : 199,
            "95944704" : 198,
            "96993280" : 183,
            "98041856" : 191,
            "99090432" : 183,
            "100139008" : 184,
            "101187584" : 173,
            "102236160" : 181,
            "103284736" : 209,
            "104333312" : 194,
            "105381888" : 165,
            "106430464" : 174,
            "107479040" : 171,
            "108527616" : 166,
            "109576192" : 173,
            "110624768" : 161,
            "111673344" : 188,
            "112721920" : 171,
            "113770496" : 181,
            "114819072" : 165,
            "115867648" : 183,
            "116916224" : 174,
            "117964800" : 139,
            "119013376" : 166,
            "120061952" : 149,
            "121110528" : 163,
            "122159104" : 161,
            "123207680" : 158,
            "124256256" : 158,
            "125304832" : 136,
            "126353408" : 152,
            "127401984" : 172,
            "128450560" : 156,
            "129499136" : 152,
            "130547712" : 165,
            "131596288" : 150,
            "132644864" : 139,
            "133693440" : 142,
            "135266304" : 274,
            "137363456" : 320,
            "139460608" : 293,
            "141557760" : 267,
            "143654912" : 259,
            "145752064" : 300,
            "147849216" : 286,
            "149946368" : 265,
            "152043520" : 237,
            "154140672" : 273,
            "156237824" : 276,
            "158334976" : 246,
            "160432128" : 265,
            "162529280" : 265,
            "164626432" : 234,
            "166723584" : 254,
            "168820736" : 243,
            "170917888" : 245,
            "173015040" : 195,
            "175112192" : 217,
            "177209344" : 235,
            "179306496" : 228,
            "181403648" : 218,
            "183500800" : 201,
            "185597952" : 215,
            "187695104" : 200,
            "189792256" : 213,
            "191889408" : 200,
            "193986560" : 192,
            "196083712" : 208,
            "198180864" : 185,
            "200278016" : 188,
            "202375168" : 183,
            "204472320" : 199,
            "206569472" : 190,
            "208666624" : 169,
            "210763776" : 189,
            "212860928" : 180,
            "214958080" : 173,
            "217055232" : 127,
            "219152384" : 154,
            "221249536" : 171,
            "223346688" : 138,
            "225443840" : 153,
            "227540992" : 168,
            "229638144" : 156,
            "231735296" : 161,
            "233832448" : 140,
            "235929600" : 163,
            "238026752" : 150,
            "240123904" : 132,
            "242221056" : 134,
            "244318208" : 122,
            "246415360" : 152,
            "248512512" : 139,
            "250609664" : 129,
            "252706816" : 122,
            "254803968" : 134,
            "256901120" : 133,
            "258998272" : 126,
            "261095424" : 135,
            "263192576" : 117,
            "265289728" : 124,
            "267386880" : 102,
            "270532608" : 221,
            "274726912" : 201,
            "278921216" : 211,
            "283115520" : 182,
            "287309824" : 175,
            "291504128" : 197,
            "295698432" : 188,
            "299892736" : 175,
            "304087040" : 175,
            "308281344" : 152,
            "312475648" : 176,
            "316669952" : 166,
            "320864256" : 157,
            "325058560" : 152,
            "329252864" : 162,
            "333447168" : 156,
            "337641472" : 150,
            "341835776" : 128,
            "346030080" : 130,
            "350224384" : 117,
            "354418688" : 126,
            "358612992" : 127,
            "362807296" : 126,
            "367001600" : 108,
            "371195904" : 94,
            "375390208" : 84,
            "379584512" : 90,
            "383778816" : 92,
            "387973120" : 104,
            "392167424" : 95,
            "396361728" : 86,
            "400556032" : 94,
            "404750336" : 88,
            "408944640" : 80,
            "413138944" : 69,
            "417333248" : 75,
            "421527552" : 86,
            "425721856" : 60,
            "429916160" : 68,
            "434110464" : 86,
            "438304768" : 72,
            "442499072" : 56,
            "446693376" : 67,
            "450887680" : 52,
            "455081984" : 64,
            "459276288" : 74,
            "463470592" : 66,
            "467664896" : 53,
            "471859200" : 63,
            "476053504" : 55,
            "480247808" : 52,
            "484442112" : 46,
            "488636416" : 58,
            "492830720" : 54,
            "497025024" : 49,
            "501219328" : 42,
            "505413632" : 36,
            "509607936" : 42,
            "513802240" : 43,
            "517996544" : 49,
            "522190848" : 51,
            "526385152" : 35,
            "530579456" : 32,
            "534773760" : 40,
            "541065216" : 71,
            "549453824" : 50,
            "557842432" : 66,
            "566231040" : 48,
            "574619648" : 48,
            "583008256" : 53,
            "591396864" : 41,
            "599785472" : 44,
            "608174080" : 27,
            "616562688" : 40,
            "624951296" : 29,
            "633339904" : 36,
            "641728512" : 27,
            "650117120" : 36,
            "658505728" : 32,
            "666894336" : 32,
            "675282944" : 25,
            "683671552" : 26,
            "692060160" : 20,
            "700448768" : 23,
            "708837376" : 22,
            "717225984" : 19,
            "725614592" : 27,
            "734003200" : 25,
            "742391808" : 10,
            "750780416" : 23,
            "759169024" : 15,
            "767557632" : 16,
            "775946240" : 14,
            "784334848" : 16,
            "792723456" : 9,
            "801112064" : 14,
            "809500672" : 14,
            "817889280" : 8,
            "826277888" : 11,
            "834666496" : 5,
            "843055104" : 7,
            "851443712" : 11,
            "859832320" : 11,
            "868220928" : 10,
            "876609536" : 3,
            "884998144" : 2,
            "893386752" : 4,
            "901775360" : 6,
            "910163968" : 9,
            "918552576" : 5,
            "926941184" : 4,
            "935329792" : 5,
            "943718400" : 5,
            "952107008" : 4,
            "960495616" : 5,
            "968884224" : 4,
            "977272832" : 2,
            "985661440" : 4,
            "994050048" : 3,
            "1002438656" : 2,
            "1010827264" : 1,
            "1019215872" : 4,
            "1027604480" : 5,
            "1035993088" : 3,
            "1044381696" : 3,
            "1061158912" : 2,
            "1069547520" : 2,
            "1082130432" : 3,
            "1098907648" : 1,
            "1115684864" : 3,
            "1132462080" : 2,
            "1149239296" : 3,
            "1166016512" : 5,
            "1199570944" : 3,
            "1233125376" : 4,
            "1249902592" : 1,
            "1283457024" : 1,
            "1300234240" : 1,
            "1317011456" : 1,
            "1333788672" : 2,
            "1350565888" : 1,
            "1384120320" : 2,
            "1400897536" : 1,
            "1451229184" : 2,
            "1518338048" : 1,
            "1551892480" : 1,
            "1585446912" : 1
          }
        },
        "lat_ns" : {
          "min" : 2870712,
          "max" : 1581062609,
          "mean" : 148721833.545780,
          "stddev" : 144356564.933973
        },
        "bw_min" : 407,
        "bw_max" : 696,
        "bw_agg" : 99.998979,
        "bw_mean" : 543.994444,
        "bw_dev" : 46.600274,
        "bw_samples" : 720,
        "iops_min" : 101,
        "iops_max" : 174,
        "iops_mean" : 135.862500,
        "iops_stddev" : 11.664968,
        "iops_samples" : 720
      },
      "trim" : {
        "io_bytes" : 0,
        "io_kbytes" : 0,
        "bw_bytes" : 0,
        "bw" : 0,
        "iops" : 0.000000,
        "runtime" : 0,
        "total_ios" : 0,
        "short_ios" : 0,
        "drop_ios" : 0,
        "slat_ns" : {
          "min" : 0,
          "max" : 0,
          "mean" : 0.000000,
          "stddev" : 0.000000
        },
        "clat_ns" : {
          "min" : 0,
          "max" : 0,
          "mean" : 0.000000,
          "stddev" : 0.000000,
          "percentile" : {
            "1.000000" : 0,
            "5.000000" : 0,
            "10.000000" : 0,
            "20.000000" : 0,
            "30.000000" : 0,
            "40.000000" : 0,
            "50.000000" : 0,
            "60.000000" : 0,
            "70.000000" : 0,
            "80.000000" : 0,
            "90.000000" : 0,
            "95.000000" : 0,
            "99.000000" : 0,
            "99.500000" : 0,
            "99.900000" : 0,
            "99.950000" : 0,
            "99.990000" : 0
          },
          "bins" : {

          }
        },
        "lat_ns" : {
          "min" : 0,
          "max" : 0,
          "mean" : 0.000000,
          "stddev" : 0.000000
        },
        "bw_min" : 0,
        "bw_max" : 0,
        "bw_agg" : 0.000000,
        "bw_mean" : 0.000000,
        "bw_dev" : 0.000000,
        "bw_samples" : 0,
        "iops_min" : 0,
        "iops_max" : 0,
        "iops_mean" : 0.000000,
        "iops_stddev" : 0.000000,
        "iops_samples" : 0
      },
      "sync" : {
        "lat_ns" : {
          "min" : 0,
          "max" : 0,
          "mean" : 0.000000,
          "stddev" : 0.000000,
          "percentile" : {
            "1.000000" : 0,
            "5.000000" : 0,
            "10.000000" : 0,
            "20.000000" : 0,
            "30.000000" : 0,
            "40.000000" : 0,
            "50.000000" : 0,
            "60.000000" : 0,
            "70.000000" : 0,
            "80.000000" : 0,
            "90.000000" : 0,
            "95.000000" : 0,
            "99.000000" : 0,
            "99.500000" : 0,
            "99.900000" : 0,
            "99.950000" : 0,
            "99.990000" : 0
          },
          "bins" : {

          }
        },
        "total_ios" : 0
      },
      "usr_cpu" : 0.485630,
      "sys_cpu" : 1.216434,
      "ctx" : 96557,
      "majf" : 0,
      "minf" : 2023,
      "iodepth_level" : {
        "1" : 0.100000,
        "2" : 0.100000,
        "4" : 0.100000,
        "8" : 0.100000,
        "16" : 0.100000,
        "32" : 99.968478,
        ">=64" : 0.000000
      },
      "latency_ns" : {
        "2" : 0.000000,
        "4" : 0.000000,
        "10" : 0.000000,
        "20" : 0.000000,
        "50" : 0.000000,
        "100" : 0.000000,
        "250" : 0.000000,
        "500" : 0.000000,
        "750" : 0.000000,
        "1000" : 0.000000
      },
      "latency_us" : {
        "2" : 0.000000,
        "4" : 0.000000,
        "10" : 0.000000,
        "20" : 0.000000,
        "50" : 0.000000,
        "100" : 0.000000,
        "250" : 0.000000,
        "500" : 0.000000,
        "750" : 0.000000,
        "1000" : 0.000000
      },
      "latency_ms" : {
        "2" : 0.000000,
        "4" : 0.092531,
        "10" : 4.534038,
        "20" : 10.557730,
        "50" : 20.628400,
        "100" : 22.687478,
        "250" : 30.029996,
        "500" : 9.711729,
        "750" : 1.427627,
        "1000" : 0.268443,
        "2000" : 0.000000,
        ">=2000" : 0.000000
      },
      "latency_depth" : 32,
      "latency_target" : 0,
      "latency_percentile" : 100.000000,
      "latency_window" : 0
    }
  ]
}
